{"Id":"40f5564f839324b9af20c295dd261007","Url":"https://wobcovid19.rijksoverheid.nl/publicaties/40f5564f839324b9af20c295dd261007/","Title":"eerste deelbesluit Wob-verzoek aantal aanwezigen in kerken periode 14 april - 26 oktober 2020","Summary":"De Minister van Justitie en Veiligheid heeft op 4 mei 2021 een eerste deelbesluit genomen op een verzoek in het kader van de Wet openbaarheid van bestuur over besluiten en uitlatingen van het kabinet\u2026","Date":"2021-05-04T15:14:45.613Z","FileName":"2021-05-04_40f5564f839324b9af20c295dd261007.json","Documents":[{"Name":"eerste deelbesluit Wob-verzoek aantal aanwezigen in kerken","Href":"eerste-deelbesluit-wob-verzoek-aantal-aanwezigen-in-kerken.pdf","Url":"https://wobcovid19.rijksoverheid.nl/publicaties/40f5564f839324b9af20c295dd261007/eerste-deelbesluit-wob-verzoek-aantal-aanwezigen-in-kerken.pdf","FileType":"PDF","Pages":"8","Size":"4 MB","DocumentType":"Wob-verzoek","Date":"04-05-2021","PageCount":8},{"Name":"inventarislijst eerste deelbesluit","Href":"inventarislijst-eerste-deelbesluit.pdf","Url":"https://wobcovid19.rijksoverheid.nl/publicaties/40f5564f839324b9af20c295dd261007/inventarislijst-eerste-deelbesluit.pdf","FileType":"PDF","Pages":"3","Size":"137 kB","DocumentType":"Wob-verzoek","Date":"04-05-2021","PageCount":3},{"Name":"Wob-documenten","Href":"wob-documenten.pdf","Url":"https://wobcovid19.rijksoverheid.nl/publicaties/40f5564f839324b9af20c295dd261007/wob-documenten.pdf","FileType":"PDF","Pages":"425","Size":"1023 MB","DocumentType":"Wob-verzoek","Date":"04-05-2021","PageCount":425}]}